MANIFEST.in
README.md
setup.py
micropython_ssd1306py.egg-info/PKG-INFO
micropython_ssd1306py.egg-info/SOURCES.txt
micropython_ssd1306py.egg-info/dependency_links.txt
micropython_ssd1306py.egg-info/top_level.txt
ssd1306py/__init__.py
ssd1306py/ascii16.py
ssd1306py/ascii16.txt
ssd1306py/ascii24.py
ssd1306py/ascii24.txt
ssd1306py/ascii32.py
ssd1306py/ascii32.txt
ssd1306py/cn.py
ssd1306py/ops.py
ssd1306py/ssd1306.py